{
  "name": "Antonio Rowe",
  "age": 63,
  "address": {
    "street": "Dito Pass",
    "city": "Puhisfuh",
    "state": "MD",
    "zip": "93062"
  },
  "contact": {
    "phone": "(622) 439-9310",
    "servicePhone": "800952919"
  },
  "birthday": "1999-09-19T11:35:43.904Z",
  "ip": "71.252.162.209",
  "foo": "bar",
  "profile": {
    "about": "Uw bad wap wavodi avezu fukag obcifam ta ru fitac wonivi wa hipho akaanom dowforog osmo rafefoh. Dol fuzu fuvo refsoca vog kezaatu worwocsip feuhar seci tejafe kebioh upfuvwu wotow guh vavah abera. Woj hivkem hi rufzu hunil gih pesju kodi remvouw liow agu mi jazup ginla. Va akiivuw movze wubiv devucguv nopu zime tinlowi wugfit lodhep juh harudnap hahaf kecsaz. Eti zoelane dokzahas kusiwoko wobpatvoz segebazo nizaglu ihsir neaked amhafro te cariv baj evdonfe ronouni okupbe. Go wod achi dec parcog suhzur judu kul gokoc col epiijiol pu ag.",
    "bio": "Zaluzib bilgiboj imji keweh fecodocu vukjugom ukepe zi pok zom pamejnu fucwa oka civjil. Ideokavo bob ur ridretlan ri ze gatfib fifatlu bujahaka ra jinepco roma irivo or uvjop vuderbo ro firwemuj. Zaf roj wuk puokobew pak ihu ikaeci mibezo tappus uj hogigen waiger ira onurejin ribruv go fol. Cetali vervirek afoohjo ri ta ijigot hadgi pir gagbon lu igla jamadav. Ror cakaubo zacwemmur ko cuoza tu ponheszih ik modugwad cetvuvic cozusar wowelze dunocop guurilev wanew vuvuduli no. Bilhibe upubokof azka topaj vebamebe olicuc pimih lagas zufribfe er jek ja ipu. Lo udovohra buj uz ekhu vot sac tidbiso keretas henozmo vu ojo uk kilfa."
  },
  "apiKey": "ee7ad5a54d1010eb64470ca08ac7c5c9f5cd094db11c0e5b9aac31bf0d5b9a58",
  "currency": {
    "code": "SDG",
    "name": "Sudan Pound"
  }
}